asaas_cdk_constructs/waf_construct/__init__.py
asaas_cdk_constructs/waf_construct/waf_construct.py
asaas_cdk_constructs-0.1.0.dist-info/METADATA
asaas_cdk_constructs-0.1.0.dist-info/WHEEL
asaas_cdk_constructs-0.1.0.dist-info/RECORD
