Metadata-Version: 2.1
Name: asaas-cdk-constructs
Version: 0.1.0
Summary: Modulo padrão Asaas para regras waf e criação de clouldfront
Author: Cesar Fernando Sturion
Author-email: cesar.sturion@asaas.com.br
Requires-Python: >=3.10,<4.0
Classifier: Programming Language :: Python :: 3
Classifier: Programming Language :: Python :: 3.10
Classifier: Programming Language :: Python :: 3.11
Requires-Dist: aws-cdk-lib (==2.104.0)
Requires-Dist: boto3 (>=1.29.6,<2.0.0)
Requires-Dist: constructs (>=10.0.0,<11.0.0)
Requires-Dist: pytest (==6.2.5)
Requires-Dist: stringcase (>=1.2.0,<2.0.0)
